[{"Year":1969,"Value":4728},{"Year":1970,"Value":5140},{"Year":1971,"Value":5418},{"Year":1972,"Value":5854},{"Year":1973,"Value":6175},{"Year":1974,"Value":6716},{"Year":1975,"Value":7157},{"Year":1976,"Value":7863},{"Year":1977,"Value":8412},{"Year":1978,"Value":9327},{"Year":1979,"Value":10272},{"Year":1980,"Value":11556},{"Year":1981,"Value":12823},{"Year":1982,"Value":13573},{"Year":1983,"Value":14320},{"Year":1984,"Value":15688},{"Year":1985,"Value":16730},{"Year":1986,"Value":17650},{"Year":1987,"Value":18402},{"Year":1988,"Value":19464},{"Year":1989,"Value":20455},{"Year":1990,"Value":21002},{"Year":1991,"Value":21555},{"Year":1992,"Value":22302},{"Year":1993,"Value":22762},{"Year":1994,"Value":23291},{"Year":1995,"Value":24275},{"Year":1996,"Value":25615},{"Year":1997,"Value":26978},{"Year":1998,"Value":29356},{"Year":1999,"Value":31343},{"Year":2000,"Value":33869},{"Year":2001,"Value":34325},{"Year":2002,"Value":35314},{"Year":2003,"Value":37078},{"Year":2004,"Value":39834},{"Year":2005,"Value":41543},{"Year":2006,"Value":43640},{"Year":2007,"Value":44546},{"Year":2008,"Value":44860},{"Year":2009,"Value":42771},{"Year":2010,"Value":43802},{"Year":2011,"Value":45977},{"Year":2012,"Value":47704},{"Year":2013,"Value":48815},{"Year":2014,"Value":51230},{"Year":2015,"Value":53679},{"Year":2016,"Value":55056},{"Year":2017,"Value":56802},{"Year":2018,"Value":58719},{"Year":2019,"Value":60845},{"Year":2020,"Value":66266}]